edalize/apicula.py
edalize/ascentlint.py
edalize/design_compiler.py
edalize/diamond.py
edalize/edatool.py
edalize/f4pga.py
edalize/gatemate.py
edalize/genus.py
edalize/ghdl.py
edalize/icarus.py
edalize/icestorm.py
edalize/ise.py
edalize/ise_reporting.py
edalize/isim.py
edalize/libero.py
edalize/mistral.py
edalize/modelsim.py
edalize/morty.py
edalize/nextpnr.py
edalize/openfpga.py
edalize/openlane.py
edalize/openroad.py
edalize/oxide.py
edalize/quartus.py
edalize/quartus_reporting.py
edalize/questaformal.py
edalize/radiant.py
edalize/reporting.py
edalize/rivierapro.py
edalize/sandpipersaas.py
edalize/slang.py
edalize/spyglass.py
edalize/symbiflow.py
edalize/symbiyosys.py
edalize/trellis.py
edalize/utils.py
edalize/vcs.py
edalize/veribleformat.py
edalize/veriblelint.py
edalize/verilator.py
edalize/version.py
edalize/vivado.py
edalize/vivado_reporting.py
edalize/vpr.py
edalize/vunit.py
edalize/vunit_hooks.py
edalize/xcelium.py
edalize/xsim.py
edalize/yosys.py
edalize/flows/edaflow.py
edalize/flows/efinity.py
edalize/flows/f4pga.py
edalize/flows/generic.py
edalize/flows/gls.py
edalize/flows/gowin.py
edalize/flows/icestorm.py
edalize/flows/lint.py
edalize/flows/sim.py
edalize/flows/vivado.py
edalize/flows/vpr.py
edalize/templates/ascentlint/Makefile.j2
edalize/templates/ascentlint/run-ascentlint.tcl.j2
edalize/templates/design_compiler/design-compiler-makefile.j2
edalize/templates/design_compiler/design-compiler-project.tcl.j2
edalize/templates/design_compiler/design-compiler-read-sources.tcl.j2
edalize/templates/genus/genus-makefile.j2
edalize/templates/genus/genus-project.tcl.j2
edalize/templates/genus/genus-read-sources.tcl.j2
edalize/templates/ghdl/Makefile.j2
edalize/templates/libero/libero-project.tcl.j2
edalize/templates/libero/libero-run.tcl.j2
edalize/templates/libero/libero-syn-user.tcl.j2
edalize/templates/openfpga/task_simulation.conf.j2
edalize/templates/openlane/openlane-makefile.j2
edalize/templates/openlane/openlane-script-tcl.j2
edalize-0.6.0.dist-info/LICENSE
edalize-0.6.0.dist-info/METADATA
edalize-0.6.0.dist-info/WHEEL
edalize-0.6.0.dist-info/top_level.txt
edalize-0.6.0.dist-info/RECORD
