Metadata-Version: 2.1
Name: edalize
Version: 0.6.0
Summary: Library for interfacing EDA tools such as simulators, linters or synthesis tools, using a common interface
Author-email: Olof Kindgren <olof@award-winning.me>
Maintainer-email: Olof Kindgren <olof@award-winning.me>
Project-URL: Homepage, https://github.com/olofk/edalize
Project-URL: Documentation, https://edalize.readthedocs.io
Project-URL: Repository, https://github.com/olofk/edalize
Project-URL: Issues, https://github.com/olofk/edalize/issues
Project-URL: Changelog, https://github.com/olofk/edalize/blob/main/NEWS
Keywords: VHDL,verilog,EDA,hdl,rtl,synthesis,FPGA,simulation,Xilinx,Altera
Classifier: Development Status :: 5 - Production/Stable
Classifier: License :: OSI Approved :: BSD License
Classifier: Topic :: Scientific/Engineering :: Electronic Design Automation (EDA)
Classifier: Topic :: Utilities
Requires-Python: <4,>=3.6
License-File: LICENSE
Requires-Dist: Jinja2>=3
